MiniFL/__init__.py
MiniFL/communications.py
MiniFL/fn.py
MiniFL/message.py
MiniFL/metrics.py
MiniFL/utils.py
MiniFL/algorithms/__init__.py
MiniFL/algorithms/cocktailsgd.py
MiniFL/algorithms/ef21.py
MiniFL/algorithms/gd.py
MiniFL/algorithms/interfaces.py
MiniFL/algorithms/marina.py
MiniFL/compressors/__init__.py
MiniFL/compressors/basic.py
MiniFL/compressors/cocktail.py
MiniFL/compressors/correlated_quantization.py
MiniFL/compressors/eden.py
MiniFL/compressors/interfaces.py
MiniFL/compressors/top_sigma.py
MiniFL/tasks/__init__.py
MiniFL/tasks/svm.py
MiniFL/tasks/tridiagonal_quadratic.py
MiniFL-0.2.1.dist-info/LICENSE
MiniFL-0.2.1.dist-info/METADATA
MiniFL-0.2.1.dist-info/WHEEL
MiniFL-0.2.1.dist-info/top_level.txt
MiniFL-0.2.1.dist-info/RECORD
